pymt5linux/__init__.py
pymt5linux/__main__.py
pymt5linux/server.py
pymt5linux-1.0.0.dist-info/LICENSE.txt
pymt5linux-1.0.0.dist-info/METADATA
pymt5linux-1.0.0.dist-info/WHEEL
pymt5linux-1.0.0.dist-info/top_level.txt
pymt5linux-1.0.0.dist-info/RECORD
