Metadata-Version: 2.2
Name: pymt5linux
Version: 1.0.0
Summary: MetaTrader5 for Linux
Home-page: https://github.com/hpdeandrade/pymt5linux
Author: Henrique Perez de Andrade
Author-email: Henrique Perez de Andrade <hpdeandrade@gmail.com>
Project-URL: Homepage, https://github.com/hpdeandrade/pymt5linux
Requires-Python: >=3.13
License-File: LICENSE.txt
Requires-Dist: rpyc
Dynamic: author
Dynamic: home-page
Dynamic: requires-python
